pqam_rmsadtandoc2023/__init__.py
pqam_rmsadtandoc2023/model.py
pqam_rmsadtandoc2023/outputDefinition.json
pqam_rmsadtandoc2023-0.1.6.dist-info/LICENSE
pqam_rmsadtandoc2023-0.1.6.dist-info/METADATA
pqam_rmsadtandoc2023-0.1.6.dist-info/WHEEL
pqam_rmsadtandoc2023-0.1.6.dist-info/top_level.txt
pqam_rmsadtandoc2023-0.1.6.dist-info/RECORD
