Metadata-Version: 2.1
Name: pqam_rmsadtandoc2023
Version: 0.1.6
Summary: PyQAlloy-compatible Model for RMSAD prediction based on Tandoc 2023 (https://doi.org/10.1038/s41524-023-00993-x)
Author-email: Adam Krajewski <ak@psu.edu>
Project-URL: Documentation, https://github.com/tandocca/Lattice-Distortion
Project-URL: Homepage, https://github.com/amkrajewski/pqam_RMSADTandoc2023
Project-URL: Bug Tracker, https://github.com/amkrajewski/pqam_RMSADTandoc2023/issues
Classifier: Programming Language :: Python :: 3
Classifier: Programming Language :: Python :: 3.9
Classifier: Programming Language :: Python :: 3.10
Classifier: Programming Language :: Python :: 3.11
Classifier: Programming Language :: Python :: 3.12
Classifier: Development Status :: 4 - Beta
Classifier: Intended Audience :: Science/Research
Classifier: License :: OSI Approved :: GNU Lesser General Public License v3 or later (LGPLv3+)
Classifier: Operating System :: OS Independent
Classifier: Topic :: Scientific/Engineering
Classifier: Topic :: Scientific/Engineering :: Artificial Intelligence
Classifier: Topic :: Scientific/Engineering :: Chemistry
Classifier: Topic :: Scientific/Engineering :: Physics
Requires-Python: >=3.9
License-File: LICENSE
Requires-Dist: pymatgen >=2024.2.20
Requires-Dist: numpy <2.0.0,>=1.25.0
